README.md
setup.py
amway_eap_packagerit/__init__.py
amway_eap_packagerit.egg-info/PKG-INFO
amway_eap_packagerit.egg-info/SOURCES.txt
amway_eap_packagerit.egg-info/dependency_links.txt
amway_eap_packagerit.egg-info/top_level.txt